aleksis/apps/stoelindeling/__init__.py
aleksis/apps/stoelindeling/apps.py
aleksis/apps/stoelindeling/forms.py
aleksis/apps/stoelindeling/frontend/index.js
aleksis/apps/stoelindeling/frontend/messages/de.json
aleksis/apps/stoelindeling/frontend/messages/en.json
aleksis/apps/stoelindeling/frontend/messages/ru.json
aleksis/apps/stoelindeling/frontend/messages/uk.json
aleksis/apps/stoelindeling/locale/.keepdir
aleksis/apps/stoelindeling/locale/ar/LC_MESSAGES/django.mo
aleksis/apps/stoelindeling/locale/ar/LC_MESSAGES/django.po
aleksis/apps/stoelindeling/locale/de_DE/LC_MESSAGES/django.mo
aleksis/apps/stoelindeling/locale/de_DE/LC_MESSAGES/django.po
aleksis/apps/stoelindeling/locale/fr/LC_MESSAGES/django.mo
aleksis/apps/stoelindeling/locale/fr/LC_MESSAGES/django.po
aleksis/apps/stoelindeling/locale/la/LC_MESSAGES/django.mo
aleksis/apps/stoelindeling/locale/la/LC_MESSAGES/django.po
aleksis/apps/stoelindeling/locale/nb_NO/LC_MESSAGES/django.mo
aleksis/apps/stoelindeling/locale/nb_NO/LC_MESSAGES/django.po
aleksis/apps/stoelindeling/locale/ru/LC_MESSAGES/django.mo
aleksis/apps/stoelindeling/locale/ru/LC_MESSAGES/django.po
aleksis/apps/stoelindeling/locale/tr_TR/LC_MESSAGES/django.mo
aleksis/apps/stoelindeling/locale/tr_TR/LC_MESSAGES/django.po
aleksis/apps/stoelindeling/locale/uk/LC_MESSAGES/django.mo
aleksis/apps/stoelindeling/locale/uk/LC_MESSAGES/django.po
aleksis/apps/stoelindeling/managers.py
aleksis/apps/stoelindeling/migrations/0001_initial.py
aleksis/apps/stoelindeling/migrations/0002_seat_auto_create.py
aleksis/apps/stoelindeling/migrations/0003_seat_negative_x_y.py
aleksis/apps/stoelindeling/migrations/0004_alter_seatingplan_subject.py
aleksis/apps/stoelindeling/migrations/0005_alter_seatingplan_room.py
aleksis/apps/stoelindeling/migrations/__init__.py
aleksis/apps/stoelindeling/model_extensions.py
aleksis/apps/stoelindeling/models.py
aleksis/apps/stoelindeling/rules.py
aleksis/apps/stoelindeling/settings.py
aleksis/apps/stoelindeling/static/.keepdir
aleksis_app_stoelindeling-2.0.dist-info/METADATA
aleksis_app_stoelindeling-2.0.dist-info/WHEEL
aleksis_app_stoelindeling-2.0.dist-info/entry_points.txt
aleksis_app_stoelindeling-2.0.dist-info/RECORD
