Metadata-Version: 2.1
Name: aleksis-app-stoelindeling
Version: 2.0
Summary: AlekSIS (School Information System) — App Stoelindeling (Create and publish seating plans)
Home-page: https://aleksis.org
License: EUPL-1.2-or-later
Author: Jonathan Weth
Author-email: dev@jonathanweth.de
Requires-Python: >=3.9,<4.0
Classifier: Environment :: Web Environment
Classifier: Intended Audience :: Education
Classifier: License :: Other/Proprietary License
Classifier: Programming Language :: Python :: 3
Classifier: Programming Language :: Python :: 3.9
Classifier: Programming Language :: Python :: 3.10
Classifier: Programming Language :: Python :: 3.11
Classifier: Topic :: Education
Requires-Dist: aleksis-app-chronos (>=3.0,<4.0)
Requires-Dist: aleksis-core (>=3.0,<4.0)
Project-URL: Documentation, https://aleksis.org/official/AlekSIS/docs/html/
Project-URL: Repository, https://edugit.org/AlekSIS/official/AlekSIS-App-Stoelindeling
